CHANGES
LICENSE
MANIFEST.in
README
build.vel
setup.py
bin/vellum
scripts/dist.vel
scripts/sample.vel
scripts/setup.py
scripts/testing.vel
tests/__init__.py
tests/bin_tests.py
tests/command_tests.py
tests/parser_tests.py
tests/press_tests.py
tests/scribe_tests.py
tests/script_tests.py
tests/test_ext/j2gen_tests.py
tests/test_ext/setup_tests.py
vellum/__init__.py
vellum/bin.py
vellum/commands.py
vellum/parser.py
vellum/press.py
vellum/scribe.py
vellum/script.py
vellum/version.py
vellum.egg-info/PKG-INFO
vellum.egg-info/SOURCES.txt
vellum.egg-info/dependency_links.txt
vellum.egg-info/top_level.txt
vellum/ext/__init__.py
vellum/ext/jinja2gen.py
vellum/ext/setup.py