Metadata-Version: 1.0
Name: vellum
Version: 0.17
Summary: A flexible small make alternative for Python programmers.
Home-page: http://www.zedshaw.com/projects/vellum
Author: Ronny Pfannschmidt
Author-email: Ronny.Pfannschmidt@gmx.de
License: UNKNOWN
Platform: UNKNOWN
